pietroalbini_sphinx_themes/__init__.py
pietroalbini_sphinx_themes/version
pietroalbini_sphinx_themes/themes/pietroalbini/theme.conf
pietroalbini_sphinx_themes/themes/pietroalbini/genindex.html
pietroalbini_sphinx_themes/themes/pietroalbini/search.html
pietroalbini_sphinx_themes/themes/pietroalbini/layout.html
pietroalbini_sphinx_themes/themes/pietroalbini/static/font-awesome-4.4.0.css
pietroalbini_sphinx_themes/themes/pietroalbini/static/theme_singlepage.js
pietroalbini_sphinx_themes/themes/pietroalbini/static/theme_search.js
pietroalbini_sphinx_themes/themes/pietroalbini/static/theme_preferences.js
pietroalbini_sphinx_themes/themes/pietroalbini/static/theme_genindex.js
pietroalbini_sphinx_themes/themes/pietroalbini/static/customizations.css_t
pietroalbini_sphinx_themes/themes/pietroalbini/static/searchtools.js_t
pietroalbini_sphinx_themes/themes/pietroalbini/static/dejavu.css
pietroalbini_sphinx_themes/themes/pietroalbini/static/theme.js
pietroalbini_sphinx_themes/themes/pietroalbini/static/hack.css
pietroalbini_sphinx_themes/themes/pietroalbini/static/pietroalbini.css
pietroalbini_sphinx_themes/themes/pietroalbini/static/fonts/font-awesome-4.4.0.ttf
pietroalbini_sphinx_themes/themes/pietroalbini/static/fonts/dejavu/regular.ttf
pietroalbini_sphinx_themes/themes/pietroalbini/static/fonts/dejavu/bold.ttf
pietroalbini_sphinx_themes/themes/pietroalbini/static/fonts/dejavu/light.ttf
pietroalbini_sphinx_themes/themes/pietroalbini/static/fonts/dejavu/regular-italic.ttf
pietroalbini_sphinx_themes/themes/pietroalbini/static/fonts/dejavu/bold-italic.ttf
pietroalbini_sphinx_themes/themes/pietroalbini/static/fonts/hack/regular.ttf
pietroalbini_sphinx_themes/themes/pietroalbini/static/fonts/hack/bold.ttf
pietroalbini_sphinx_themes/themes/pietroalbini/static/fonts/hack/regular-italic.ttf
pietroalbini_sphinx_themes/themes/pietroalbini/static/fonts/hack/bold-italic.ttf
pietroalbini_sphinx_themes-1.3.1.dist-info/WHEEL
pietroalbini_sphinx_themes-1.3.1.dist-info/metadata.json
pietroalbini_sphinx_themes-1.3.1.dist-info/METADATA
pietroalbini_sphinx_themes-1.3.1.dist-info/RECORD
pietroalbini_sphinx_themes-1.3.1.dist-info/DESCRIPTION.rst
pietroalbini_sphinx_themes-1.3.1.dist-info/top_level.txt
