Metadata-Version: 2.0
Name: pietroalbini-sphinx-themes
Version: 1.3.1
Summary: Sphinx themes for my own projects
Home-page: https://github.com/pietroalbini/sphinx-themes
Author: Pietro Albini
Author-email: pietro@pietroalbini.io
License: MIT
Platform: UNKNOWN
Requires-Dist: sphinx
